<annotation>
	<folder></folder>
	<filename>IMG_8414_JPEG.rf.3613f40077fa52817fdb4d0cb8570dc7.jpg</filename>
	<path>IMG_8414_JPEG.rf.3613f40077fa52817fdb4d0cb8570dc7.jpg</path>
	<source>
		<database>roboflow.com</database>
	</source>
	<size>
		<width>640</width>
		<height>640</height>
		<depth>3</depth>
	</size>
	<segmented>0</segmented>
	<object>
		<name>lays</name>
		<pose>Unspecified</pose>
		<truncated>0</truncated>
		<difficult>0</difficult>
		<occluded>0</occluded>
		<bndbox>
			<xmin>133</xmin>
			<xmax>522</xmax>
			<ymin>135</ymin>
			<ymax>498</ymax>
		</bndbox>
		<polygon>
			<x1>329.068888</x1>
			<y1>494.946472</y1>
			<x2>330.340706</x2>
			<y2>496.240123</y2>
			<x3>344.090706</x3>
			<y3>496.720283</y3>
			<x4>345.318888</x4>
			<y4>495.513934</y4>
			<x5>354.068888</x5>
			<y5>495.819491</y5>
			<x6>360.27525</x6>
			<y6>493.537746</y6>
			<x7>366.52525</x7>
			<y7>493.756001</y7>
			<x8>367.753431</x8>
			<y8>492.549652</y8>
			<x9>376.481612</x9>
			<y9>491.605208</y9>
			<x10>377.709794</x10>
			<y10>490.398859</y10>
			<x11>386.437975</x11>
			<y11>489.454416</y11>
			<x12>392.622518</x12>
			<y12>485.922671</y12>
			<x13>401.328881</x13>
			<y13>483.728228</y13>
			<x14>416.197968</x14>
			<y14>476.752039</y14>
			<x15>418.65433</x15>
			<y15>474.339341</y15>
			<x16>421.15433</x16>
			<y16>474.426643</y16>
			<x17>433.501598</x17>
			<y17>466.113153</y17>
			<x18>435.936142</x18>
			<y18>462.450454</y18>
			<x19>439.686142</x19>
			<y19>462.581407</y19>
			<x20>454.467953</x20>
			<y20>450.605219</y20>
			<x21>468.196134</x21>
			<y21>449.835379</y21>
			<x22>480.608859</x22>
			<y22>445.271889</y22>
			<x23>492.254761</x23>
			<y23>432.561573</y23>
			<x24>495.895667</x24>
			<y24>426.442526</y24>
			<x25>495.85203</x25>
			<y25>423.942526</y25>
			<x26>501.971117</x26>
			<y26>416.660781</y26>
			<x27>501.927479</x27>
			<y27>414.160781</y27>
			<x28>505.568385</x28>
			<y28>408.041734</y28>
			<x29>506.687472</x29>
			<y29>400.585385</y29>
			<x30>511.53474</x30>
			<y30>392.009989</y30>
			<x31>511.469283</x31>
			<y31>388.259989</y31>
			<x32>515.044733</x32>
			<y32>378.390941</y32>
			<x33>516.032907</x33>
			<y33>363.434592</y33>
			<x34>517.261088</x34>
			<y34>362.228243</y34>
			<x35>518.336537</x35>
			<y35>352.271894</y35>
			<x36>519.564719</x36>
			<y36>351.065545</y36>
			<x37>519.411987</x37>
			<y37>342.315545</y37>
			<x38>520.640168</x38>
			<y38>341.109196</y38>
			<x39>520.029241</x39>
			<y39>306.109196</y39>
			<x40>518.757422</x40>
			<y40>304.815545</y40>
			<x41>518.60469</x41>
			<y41>296.065545</y41>
			<x42>517.332871</x42>
			<y42>294.771894</y42>
			<x43>514.614683</x43>
			<y43>282.184592</y43>
			<x44>510.73377</x44>
			<y44>274.55364</y44>
			<x45>509.374676</x45>
			<y45>268.259989</y45>
			<x46>502.906487</x46>
			<y46>255.541734</y46>
			<x47>499.091031</x47>
			<y47>251.660781</y47>
			<x48>497.775574</x48>
			<y48>247.86713</y48>
			<x49>495.253756</x49>
			<y49>246.529828</y49>
			<x50>491.41648</x50>
			<y50>241.398875</y50>
			<x51>486.220111</x51>
			<y51>229.974271</y51>
			<x52>479.839198</x52>
			<y52>222.256016</y52>
			<x53>475.958285</x53>
			<y53>214.625064</y53>
			<x54>468.327372</x54>
			<y54>206.863158</y54>
			<x55>463.196459</x55>
			<y55>199.188554</y55>
			<x56>437.16781</x56>
			<y56>175.168709</y56>
			<x57>403.068709</x57>
			<y57>153.990133</y57>
			<x58>394.275071</x58>
			<y58>151.184577</y58>
			<x59>390.481434</x59>
			<y59>148.553624</y59>
			<x60>387.981434</x60>
			<y60>148.466322</y60>
			<x61>384.187796</x61>
			<y61>145.835369</y61>
			<x62>381.687796</x62>
			<y62>145.748067</y62>
			<x63>377.894158</x63>
			<y63>143.117114</y63>
			<x64>359.078702</x64>
			<y64>138.71235</y64>
			<x65>357.806883</x65>
			<y65>137.418699</y65>
			<x66>339.035064</x66>
			<y66>135.513934</y66>
			<x67>337.763245</x67>
			<y67>134.220283</y67>
			<x68>297.785064</x68>
			<y68>134.073452</y68>
			<x69>296.556883</x69>
			<y69>135.279802</y69>
			<x70>290.306883</x70>
			<y70>135.061547</y70>
			<x71>284.100521</x71>
			<y71>137.343292</y71>
			<x72>280.350521</x72>
			<y72>137.212339</y72>
			<x73>279.12234</x73>
			<y73>138.418688</y73>
			<x74>275.37234</x74>
			<y74>138.287735</y74>
			<x75>274.144158</x75>
			<y75>139.494084</y75>
			<x76>270.394158</x76>
			<y76>139.363131</y76>
			<x77>254.275071</x77>
			<y77>146.295669</y77>
			<x78>251.775071</x78>
			<y78>146.208367</y78>
			<x79>219.580535</x79>
			<y79>162.573442</y79>
			<x80>202.320542</x80>
			<y80>175.712328</y80>
			<x81>193.745093</x81>
			<y81>185.406772</y81>
			<x82>173.723274</x82>
			<y82>183.458356</y82>
			<x83>163.810549</x83>
			<y83>188.109149</y83>
			<x84>152.186466</x84>
			<y84>202.069464</y84>
			<x85>141.329205</x85>
			<y85>224.176606</y85>
			<x86>140.188299</x86>
			<y86>230.382955</y86>
			<x87>138.960118</x87>
			<y87>231.589304</y87>
			<x88>139.025574</x88>
			<y88>235.339304</y88>
			<x89>136.61285</x89>
			<y89>240.252002</y89>
			<x90>136.700125</x90>
			<y90>245.252002</y90>
			<x91>134.309219</x91>
			<y91>251.4147</y91>
			<x92>134.418313</x92>
			<y92>257.6647</y92>
			<x93>133.190132</x93>
			<y93>258.871049</y93>
			<x94>133.321045</x94>
			<y94>266.371049</y94>
			<x95>132.092864</x95>
			<y95>267.577398</y95>
			<x96>132.616516</x96>
			<y96>297.577398</y96>
			<x97>133.888335</x97>
			<y97>298.871049</y97>
			<x98>134.041067</x98>
			<y98>307.621049</y98>
			<x99>135.312885</x99>
			<y99>308.9147</y99>
			<x100>136.824711</x100>
			<y100>323.958351</y100>
			<x101>140.749262</x101>
			<y101>334.089304</y101>
			<x102>140.836537</x102>
			<y102>339.089304</y102>
			<x103>143.423813</x103>
			<y103>344.176606</y103>
			<x104>143.46745</x104>
			<y104>346.676606</y104>
			<x105>152.479276</x105>
			<y105>361.982163</y105>
			<x106>156.294733</x106>
			<y106>365.863115</y106>
			<x107>156.33837</x107>
			<y107>368.363115</y107>
			<x108>161.491102</x108>
			<y108>377.287719</y108>
			<x109>161.53474</x109>
			<y109>379.787719</y109>
			<x110>169.296566</x110>
			<y110>395.049625</y110>
			<x111>171.840204</x111>
			<y111>397.636927</y111>
			<x112>171.883841</x112>
			<y112>400.136927</y112>
			<x113>176.992935</x113>
			<y113>406.561531</y113>
			<x114>178.308392</x114>
			<y114>410.355182</y114>
			<x115>193.635674</x115>
			<y115>429.628993</y115>
			<x116>195.521584</x116>
			<y116>430.31947</y116>
			<x117>205.696134</x117>
			<y117>440.668677</y117>
			<x118>206.946134</x118>
			<y118>440.712328</y118>
			<x119>209.511591</x119>
			<y119>444.54963</y119>
			<x120>224.70796</x120>
			<y120>456.323442</y120>
			<x121>228.479779</x121>
			<y121>457.704395</y121>
			<x122>233.567055</x122>
			<y122>462.878999</y122>
			<x123>260.057062</x123>
			<y123>477.545669</y123>
			<x124>266.328881</x124>
			<y124>479.013924</y124>
			<x125>270.122518</x125>
			<y125>481.644877</y125>
			<x126>272.622518</x126>
			<y126>481.732178</y126>
			<x127>275.166156</x127>
			<y127>484.31948</y127>
			<x128>278.916156</x128>
			<y128>484.450433</y128>
			<x129>282.709794</x129>
			<y129>487.081386</y129>
			<x130>286.459794</x130>
			<y130>487.212339</y130>
			<x131>287.731612</x131>
			<y131>488.50599</y131>
			<x132>292.731612</x132>
			<y132>488.680594</y132>
			<x133>299.02525</x133>
			<y133>491.398849</y133>
			<x134>302.77525</x134>
			<y134>491.529802</y134>
			<x135>304.047069</x135>
			<y135>492.823452</y135>
			<x136>312.797069</x136>
			<y136>493.129009</y136>
			<x137>314.068888</x137>
			<y137>494.42266</y137>
			<x138>323.454797</x138>
			<y138>495.375042</y138>
			<x139>325.340706</x139>
			<y139>496.065519</y139>
			<x140>326.568888</x140>
			<y140>494.85917</y140>
			<x141>329.068888</x141>
			<y141>494.946472</y141>
		</polygon>
	</object>
</annotation>
